mogwai/__init__.py
mogwai/config.py
mogwai/graph_config.py
mogwai/graphs.py
mogwai/mogwai_cmd.py
mogwai/version.py
mogwai/core/__init__.py
mogwai/core/exceptions.py
mogwai/core/hd_index.py
mogwai/core/mogwaigraph.py
mogwai/core/traversal.py
mogwai/core/traverser.py
mogwai/core/steps/__init__.py
mogwai/core/steps/base_steps.py
mogwai/core/steps/branch_steps.py
mogwai/core/steps/enums.py
mogwai/core/steps/filter_steps.py
mogwai/core/steps/flatmap_steps.py
mogwai/core/steps/io_step.py
mogwai/core/steps/map_steps.py
mogwai/core/steps/modulation_steps.py
mogwai/core/steps/predicates.py
mogwai/core/steps/start_steps.py
mogwai/core/steps/statics.py
mogwai/core/steps/terminal_steps.py
mogwai/decorators/__init__.py
mogwai/decorators/decorators.py
mogwai/examples/__init__.py
mogwai/examples/modern.py
mogwai/examples/schema.py
mogwai/io/__init__.py
mogwai/io/mogwai_io.py
mogwai/lod/__init__.py
mogwai/lod/yamlable.py
mogwai/parser/__init__.py
mogwai/parser/excel_converter.py
mogwai/parser/filesystem.py
mogwai/parser/graphml_converter.py
mogwai/parser/json_converter.py
mogwai/parser/pdfgraph.py
mogwai/parser/powerpoint_converter.py
mogwai/schema/__init__.py
mogwai/schema/graph_schema.py
mogwai/schema/nx_to_rdf.py
mogwai/utils/__init__.py
mogwai/utils/graph_summary.py
mogwai/utils/type_utils.py
mogwai/web/__init__.py
mogwai/web/i18n_config.py
mogwai/web/node_view.py
mogwai/web/server.py
mogwai/web/resources/i18n/de.yaml
mogwai/web/resources/i18n/en.yaml
mogwai_examples/UB-10ML-mogwai.ipynb
mogwai_examples/air-routes-latest.graphml
mogwai_examples/air-routes-small-latest.graphml
mogwai_examples/example_graph_configs.yaml
mogwai_examples/live_demo.ipynb
mogwai_examples/lorem.pdf
mogwai_examples/modern-schema.yaml
mogwai_examples/mogwai.ipynb
mogwai_examples/royal-family.json
mogwai_examples/test_rdf.rdf
mogwai_examples/weimar.graphml
pymogwai-0.1.1.dist-info/METADATA
pymogwai-0.1.1.dist-info/WHEEL
pymogwai-0.1.1.dist-info/entry_points.txt
pymogwai-0.1.1.dist-info/licenses/LICENSE
pymogwai-0.1.1.dist-info/RECORD
