Metadata-Version: 2.4
Name: pyMogwai
Version: 0.1.1
Summary: PyMogwai is a Python-based implementation of the Gremlin graph traversal language, designed to create and handle knowledge graphs entirely in Python without the need for an external Gremlin server.
Project-URL: Home, https://github.com/juupje/pyMogwai
Project-URL: Documentation, https://cr.bitplan.com/index.php/pyMogwai
Project-URL: Source, https://github.com/juupje/pyMogwai
Author-email: Joep Geuskens <joep.geuskens@rwth-aachen.de>, Wolfgang Fahl <wf@bitplan.com>
Maintainer-email: Joep Geuskens <joep.geuskens@rwth-aachen.de>, Wolfgang Fahl <wf@bitplan.com>
License-Expression: Apache-2.0
License-File: LICENSE
Keywords: graph traversal,gremlin,knowledge graph,nicegui,pyMogwai
Classifier: Development Status :: 4 - Beta
Classifier: Environment :: Web Environment
Classifier: Intended Audience :: Developers
Classifier: Intended Audience :: Education
Classifier: Intended Audience :: Science/Research
Classifier: License :: OSI Approved :: Apache Software License
Classifier: Operating System :: OS Independent
Classifier: Programming Language :: Python :: 3 :: Only
Classifier: Programming Language :: Python :: 3.10
Classifier: Programming Language :: Python :: 3.11
Classifier: Programming Language :: Python :: 3.12
Classifier: Topic :: Software Development :: Libraries :: Python Modules
Requires-Python: >=3.10
Requires-Dist: dacite>=1.8.1
Requires-Dist: dataclasses-json>=0.6.7
Requires-Dist: networkx==3.3
Provides-Extra: converters
Requires-Dist: openpyxl>=3.1.5; extra == 'converters'
Requires-Dist: pandas>=2.3.1; extra == 'converters'
Requires-Dist: pypdf>=4.2.0; extra == 'converters'
Requires-Dist: pysemanticslides>=0.3.2; extra == 'converters'
Provides-Extra: draw
Requires-Dist: pydot>=2.0.0; extra == 'draw'
Provides-Extra: graphviz
Requires-Dist: pygraphviz>=0.20.3; extra == 'graphviz'
Provides-Extra: gui
Requires-Dist: ngwidgets>=0.29.1; extra == 'gui'
Requires-Dist: nicegui>=2.21.1; extra == 'gui'
Requires-Dist: python-i18n>=0.3.9; extra == 'gui'
Provides-Extra: lod
Requires-Dist: pylodstorage>=0.17.0; extra == 'lod'
Provides-Extra: test
Requires-Dist: green; extra == 'test'
